sigma/backends/datadog/__init__.py
sigma/backends/datadog/datadog.py
sigma/pipelines/datadog/__init__.py
sigma/pipelines/datadog/datadog.py
pysigma_backend_datadog-0.3.1.dist-info/LICENSE
pysigma_backend_datadog-0.3.1.dist-info/LICENSE-3rdparty.csv
pysigma_backend_datadog-0.3.1.dist-info/METADATA
pysigma_backend_datadog-0.3.1.dist-info/NOTICE.md
pysigma_backend_datadog-0.3.1.dist-info/WHEEL
pysigma_backend_datadog-0.3.1.dist-info/RECORD
