Metadata-Version: 2.3
Name: pySigma-backend-datadog
Version: 0.3.1
Summary: pySigma Datadog backend
License: LGPL-3.0-only
Author: Datadog Cloud SIEM
Author-email: team-cloudsiembackend@datadoghq.com
Requires-Python: >=3.8,<4.0
Classifier: License :: OSI Approved :: GNU Lesser General Public License v3 (LGPLv3)
Classifier: Programming Language :: Python :: 3
Classifier: Programming Language :: Python :: 3.8
Classifier: Programming Language :: Python :: 3.9
Classifier: Programming Language :: Python :: 3.10
Classifier: Programming Language :: Python :: 3.11
Classifier: Programming Language :: Python :: 3.12
Classifier: Programming Language :: Python :: 3.13
Requires-Dist: pysigma (>=0.11,<0.12)
Project-URL: Repository, https://github.com/DatadogHQ/pySigma-backend-datadog
